{"Planted Aggressive.CO2 Pressure": {"last_state_change": 1503781266, "last_state_change_value": 25.338631855220186, "last_update": 1503781266}, "Planted Community.UV Filter": {"last_state_change_value": 1, "last_state_change": 1503777183, "last_update": 1503777183}, "Planted Community.Finnex 24/7": {"last_state_change_value": 1, "last_state_change": 1503777183, "last_update": 1503777183}, "Planted Aggressive.Finnex 24/7": {"last_state_change": 1503777189, "last_state_change_value": 1, "last_update": 1503777189}, "Planted Aggressive.Temperature": {"last_state_change": 1503781266, "last_state_change_value": 79.1366, "last_update": 1503781266}, "Planted Community.Power Head": {"last_state_change_value": 0, "last_state_change": 1503781200, "last_update": 1503781200}, "Planted Community.CO2 Pressure": {"last_state_change": 1503781259, "last_state_change_value": 26.060528885769216, "last_update": 1503781259}, "Planted Community.Temperature": {"last_state_change": 1503781259, "last_state_change_value": 78.6866, "last_update": 1503781259}, "Planted Aggressive.CO2 Solenoid": {"last_state_change_value": 1, "last_state_change": 1503777189, "last_update": 1503777189}, "Planted Aggressive.UV Filter": {"last_state_change": 1503777189, "last_state_change_value": 1, "last_update": 1503777189}, "sunrise_sync": {"last_state_change_value": {"sunset_raw": 1503791139, "sunset": "7:45 PM", "sunrise_raw": 1503745138, "sunrise": "6:58 AM"}, "last_state_change": 1503759369, "last_update": 1503759369}, "Planted Community.CO2 Solenoid": {"last_state_change_value": 1, "last_state_change": 1503777182, "last_update": 1503777182}}